dicom_ups/__init__.py
dicom_ups/dicom_handlers.py
dicom_ups/options.py
dicom_ups/ups_steps.py
dicom_ups-0.0.8.dist-info/METADATA
dicom_ups-0.0.8.dist-info/WHEEL
dicom_ups-0.0.8.dist-info/RECORD
